MANIFEST.in
README.rst
README.txt
setup.py
collective/__init__.py
collective.xmpp.core.egg-info/PKG-INFO
collective.xmpp.core.egg-info/SOURCES.txt
collective.xmpp.core.egg-info/dependency_links.txt
collective.xmpp.core.egg-info/entry_points.txt
collective.xmpp.core.egg-info/namespace_packages.txt
collective.xmpp.core.egg-info/not-zip-safe
collective.xmpp.core.egg-info/requires.txt
collective.xmpp.core.egg-info/top_level.txt
collective/xmpp/__init__.py
collective/xmpp/core/__init__.py
collective/xmpp/core/client.py
collective/xmpp/core/component.py
collective/xmpp/core/configure.zcml
collective/xmpp/core/dbconfig.py
collective/xmpp/core/decorators.py
collective/xmpp/core/exceptions.py
collective/xmpp/core/httpb.py
collective/xmpp/core/interfaces.py
collective/xmpp/core/protocols.py
collective/xmpp/core/reactor.py
collective/xmpp/core/reactor.zcml
collective/xmpp/core/settings.py
collective/xmpp/core/storage.py
collective/xmpp/core/testing.py
collective/xmpp/core/browser/__init__.py
collective/xmpp/core/browser/configure.zcml
collective/xmpp/core/browser/controlpanel.py
collective/xmpp/core/browser/loader.py
collective/xmpp/core/browser/logger.pt
collective/xmpp/core/browser/transforms.py
collective/xmpp/core/browser/user_details.pt
collective/xmpp/core/browser/userinfo.py
collective/xmpp/core/browser/usersetup.pt
collective/xmpp/core/browser/xmppsettings.pt
collective/xmpp/core/browser/css/styles.css
collective/xmpp/core/browser/gritter/gritter-close-ie6.gif
collective/xmpp/core/browser/gritter/gritter-long.png
collective/xmpp/core/browser/gritter/gritter.png
collective/xmpp/core/browser/gritter/jquery.gritter.css
collective/xmpp/core/browser/gritter/jquery.gritter.min.js
collective/xmpp/core/browser/images/chat_icon.png
collective/xmpp/core/browser/images/icon-xmpp.png
collective/xmpp/core/browser/images/location_icon.png
collective/xmpp/core/browser/images/reply_icon.png
collective/xmpp/core/browser/images/search_icon.png
collective/xmpp/core/browser/images/stream_icon.png
collective/xmpp/core/browser/js/jarnxmpp.core.handlers.js
collective/xmpp/core/browser/js/strophe.js
collective/xmpp/core/locales/collective.xmpp.core.pot
collective/xmpp/core/locales/el/LC_MESSAGES/collective.xmpp.core.po
collective/xmpp/core/locales/en/LC_MESSAGES/collective.xmpp.core.po
