Metadata-Version: 1.0
Name: collective.xmpp.core
Version: 0.3
Summary: Enables core functionality for XMPP-enabled Plone add-ons.
Home-page: https://github.com/collective/collective.xmpp.core
Author: Plone Community
Author-email: plone-developers@lists.sourceforge.net
License: GPL
Keywords: plone xmpp twisted
Platform: UNKNOWN
Classifier: Development Status :: 4 - Beta
Classifier: Framework :: Plone :: 4.1
Classifier: Framework :: Plone :: 4.2
Classifier: Framework :: Plone :: 4.3
Classifier: Intended Audience :: Developers
Classifier: Programming Language :: Python
